scmaui/__init__.py
scmaui/__main__.py
scmaui/cli.py
scmaui/data.py
scmaui/ensembles.py
scmaui/layers.py
scmaui/model_components.py
scmaui/utils.py
scmaui/vae_models.py
scmaui/resources/gtx.h5ad
scmaui/resources/peaks.h5ad
scmaui-0.0.6.dist-info/AUTHORS.rst
scmaui-0.0.6.dist-info/LICENSE
scmaui-0.0.6.dist-info/METADATA
scmaui-0.0.6.dist-info/WHEEL
scmaui-0.0.6.dist-info/entry_points.txt
scmaui-0.0.6.dist-info/top_level.txt
scmaui-0.0.6.dist-info/RECORD
