Metadata-Version: 2.1
Name: scmaui
Version: 0.0.6
Summary: Negative multinomial variational auto-encoder
Home-page: https://github.com/wkopp/scmaui
Author: Wolfgang Kopp
Author-email: wolfgang.kopp@mdc-berlin.de
License: LGPL-3.0-or-later
Project-URL: Documentation, https://scmaui.readthedocs.io/
Project-URL: Changelog, https://scmaui.readthedocs.io/en/latest/changelog.html
Project-URL: Issue Tracker, https://github.com/wkopp/scmaui/issues
Requires-Python: >=2.7, !=3.0.*, !=3.1.*, !=3.2.*, !=3.3.*, !=3.4.*
License-File: LICENSE
License-File: AUTHORS.rst
Requires-Dist: scikit-learn
Requires-Dist: tensorflow (==2.9.0)
Requires-Dist: numpy (<1.24)
Requires-Dist: protobuf (==3.19.*)
Requires-Dist: pandas
Requires-Dist: scipy
Requires-Dist: scanpy
Requires-Dist: anndata
Requires-Dist: louvain
Requires-Dist: igraph
